cliify/CommandWrapper.py
cliify/__init__.py
cliify/demo.py
cliify/splitHelper.py
cliify/completers/__init__.py
cliify/completers/prompt_toolkit.py
cliify/completers/textual.py
cliify/test/test_command_wrapper.py
cliify/test/test_helpers.py
cliify/ui/LogRouter.py
cliify/ui/__init__.py
cliify/ui/prompt_toolkit/Console.py
cliify/ui/prompt_toolkit/SplitConsole.py
cliify/ui/prompt_toolkit/__init__.py
cliify/ui/textual/SplitConsole.py
cliify/ui/textual/__init__.py
cliify-0.3.7.dist-info/METADATA
cliify-0.3.7.dist-info/WHEEL
cliify-0.3.7.dist-info/entry_points.txt
cliify-0.3.7.dist-info/licenses/LICENSE
cliify-0.3.7.dist-info/RECORD
