Metadata-Version: 2.4
Name: cliify
Version: 0.3.7
Summary: Package for creating a CLI from classes
Project-URL: homepage, https://gitlab.com/JasonBerger/cliify
Project-URL: repository, https://gitlab.com/JasonBerger/cliify
Author-email: Jason Berger <berg472@gmail.com>
License: MIT
License-File: LICENSE
Requires-Python: >=3.7
Requires-Dist: termcolor>=1.1.0
Provides-Extra: full
Requires-Dist: prompt-toolkit>=3.0.0; extra == 'full'
Provides-Extra: prompt-toolkit
Requires-Dist: prompt-toolkit>=3.0.0; extra == 'prompt-toolkit'
Provides-Extra: textual
Requires-Dist: textual; extra == 'textual'
Requires-Dist: textual-autocomplete; extra == 'textual'
